rootfilespec/__init__.py
rootfilespec/_version.py
rootfilespec/_version.pyi
rootfilespec/container.py
rootfilespec/cpptype.py
rootfilespec/dispatch.py
rootfilespec/dynamic.py
rootfilespec/py.typed
rootfilespec/serializable.py
rootfilespec/structutil.py
rootfilespec/bootstrap/RAnchor.py
rootfilespec/bootstrap/TBasket.py
rootfilespec/bootstrap/TDatime.py
rootfilespec/bootstrap/TDirectory.py
rootfilespec/bootstrap/TFile.py
rootfilespec/bootstrap/TKey.py
rootfilespec/bootstrap/TList.py
rootfilespec/bootstrap/TObject.py
rootfilespec/bootstrap/TStreamerInfo.py
rootfilespec/bootstrap/TUUID.py
rootfilespec/bootstrap/__init__.py
rootfilespec/bootstrap/array.py
rootfilespec/bootstrap/assumed.py
rootfilespec/bootstrap/compression.py
rootfilespec/bootstrap/double32.py
rootfilespec/bootstrap/streamedobject.py
rootfilespec/bootstrap/strings.py
rootfilespec/generated/__init__.py
rootfilespec/rntuple/RFrame.py
rootfilespec/rntuple/RLocator.py
rootfilespec/rntuple/RNTuple.py
rootfilespec/rntuple/RPage.py
rootfilespec/rntuple/__init__.py
rootfilespec/rntuple/envelope.py
rootfilespec/rntuple/footer.py
rootfilespec/rntuple/header.py
rootfilespec/rntuple/pagelist.py
rootfilespec/rntuple/pagelocations.py
rootfilespec/rntuple/schema.py
rootfilespec-0.0.3.dist-info/METADATA
rootfilespec-0.0.3.dist-info/WHEEL
rootfilespec-0.0.3.dist-info/licenses/LICENSE
rootfilespec-0.0.3.dist-info/RECORD
