Metadata-Version: 2.4
Name: rootfilespec
Version: 0.0.3
Summary: A format specification for ROOT files
Project-URL: Homepage, https://github.com/nsmith-/rootfilespec
Project-URL: Bug Tracker, https://github.com/nsmith-/rootfilespec/issues
Project-URL: Discussions, https://github.com/nsmith-/rootfilespec/discussions
Project-URL: Changelog, https://github.com/nsmith-/rootfilespec/releases
Author-email: Nick Smith <nick.smith@cern.ch>
License-File: LICENSE
Classifier: Development Status :: 1 - Planning
Classifier: Intended Audience :: Developers
Classifier: Intended Audience :: Science/Research
Classifier: License :: OSI Approved :: BSD License
Classifier: Operating System :: OS Independent
Classifier: Programming Language :: Python
Classifier: Programming Language :: Python :: 3
Classifier: Programming Language :: Python :: 3 :: Only
Classifier: Programming Language :: Python :: 3.10
Classifier: Programming Language :: Python :: 3.11
Classifier: Programming Language :: Python :: 3.12
Classifier: Programming Language :: Python :: 3.13
Classifier: Topic :: Scientific/Engineering
Classifier: Typing :: Typed
Requires-Python: >=3.10
Requires-Dist: cramjam
Requires-Dist: numpy
Requires-Dist: typing-extensions
Requires-Dist: xxhash
Provides-Extra: dev
Requires-Dist: pytest-cov>=3; extra == 'dev'
Requires-Dist: pytest>=6; extra == 'dev'
Requires-Dist: scikit-hep-testdata; extra == 'dev'
Provides-Extra: docs
Requires-Dist: furo>=2023.08.17; extra == 'docs'
Requires-Dist: myst-parser>=0.13; extra == 'docs'
Requires-Dist: sphinx-autodoc-typehints; extra == 'docs'
Requires-Dist: sphinx-copybutton; extra == 'docs'
Requires-Dist: sphinx>=7.0; extra == 'docs'
Provides-Extra: test
Requires-Dist: pytest-cov>=3; extra == 'test'
Requires-Dist: pytest>=6; extra == 'test'
Requires-Dist: scikit-hep-testdata; extra == 'test'
